bilix/__init__.py
bilix/__main__.py
bilix/_process.py
bilix/exception.py
bilix/ffmpeg.py
bilix/log.py
bilix/utils.py
bilix/cli/assign.py
bilix/cli/main.py
bilix/download/base_downloader.py
bilix/download/base_downloader_m3u8.py
bilix/download/base_downloader_part.py
bilix/download/utils.py
bilix/progress/abc.py
bilix/progress/cli_progress.py
bilix/progress/ws_progress.py
bilix/sites/bilibili/__init__.py
bilix/sites/bilibili/api.py
bilix/sites/bilibili/api_test.py
bilix/sites/bilibili/downloader.py
bilix/sites/bilibili/downloader_test.py
bilix/sites/bilibili/informer.py
bilix/sites/bilibili/informer_test.py
bilix/sites/bilibili/utils.py
bilix/sites/bilibili/utils_test.py
bilix/sites/cctv/__init__.py
bilix/sites/cctv/api.py
bilix/sites/cctv/api_test.py
bilix/sites/cctv/downloader.py
bilix/sites/douyin/__init__.py
bilix/sites/douyin/api.py
bilix/sites/douyin/api_test.py
bilix/sites/douyin/downloader.py
bilix/sites/douyin/downloader_test.py
bilix/sites/hanime1/__init__.py
bilix/sites/hanime1/api.py
bilix/sites/hanime1/api_test.py
bilix/sites/hanime1/downloader.py
bilix/sites/jable/__init__.py
bilix/sites/jable/api.py
bilix/sites/jable/api_test.py
bilix/sites/jable/downloader.py
bilix/sites/tiktok/__init__.py
bilix/sites/tiktok/api.py
bilix/sites/tiktok/api_test.py
bilix/sites/tiktok/downloader.py
bilix/sites/tiktok/downloader_test.py
bilix/sites/yhdmp/__init__.py
bilix/sites/yhdmp/api.py
bilix/sites/yhdmp/api_test.py
bilix/sites/yhdmp/downloader.py
bilix/sites/yhdmp/yhdmp.js
bilix/sites/yinghuacd/__init__.py
bilix/sites/yinghuacd/api.py
bilix/sites/yinghuacd/api_test.py
bilix/sites/yinghuacd/downloader.py
bilix/sites/youtube/__init__.py
bilix/sites/youtube/api.py
bilix/sites/youtube/api_test.py
bilix/sites/youtube/downloader.py
bilix-0.18.9.dist-info/METADATA
bilix-0.18.9.dist-info/WHEEL
bilix-0.18.9.dist-info/entry_points.txt
bilix-0.18.9.dist-info/licenses/LICENSE
bilix-0.18.9.dist-info/RECORD
