Metadata-Version: 2.3
Name: bilix
Version: 0.18.9
Summary: ⚡️Lightning-fast asynchronous download tool for bilibili and more
Project-URL: Homepage, https://github.com/HFrost0/bilix
Author-email: HFrost0 <hhlfrost@gmail.com>
License-Expression: Apache-2.0
License-File: LICENSE
Classifier: Programming Language :: Python :: 3
Classifier: Programming Language :: Python :: 3 :: Only
Classifier: Programming Language :: Python :: 3.8
Classifier: Programming Language :: Python :: 3.9
Classifier: Programming Language :: Python :: 3.10
Classifier: Programming Language :: Python :: 3.11
Classifier: Programming Language :: Python :: 3.12
Requires-Python: >=3.8
Requires-Dist: aiofiles>=0.8.0
Requires-Dist: anyio
Requires-Dist: browser-cookie3>=0.17.1
Requires-Dist: bs4
Requires-Dist: click>=8.0.3
Requires-Dist: danmakuc>=0.3.5
Requires-Dist: httpx[http2]>=0.23.3
Requires-Dist: json5
Requires-Dist: m3u8>=3.5.0
Requires-Dist: pycryptodome
Requires-Dist: pydantic>=2.5.3
Requires-Dist: pymp4>=1.2.0
Requires-Dist: rich
